{"10": {"FDR": 0.0, "Power": 0.6, "Temporal_FDR": 0.0, "Temporal_Power": 0.6, "Average_Window_FDR": 0.0, "Average_Window_Power": 0.7019607843137255, "Window_Overlap": {"0": 0.8529411764705883, "3": 1.0, "4": 0.7}}, "20": {"FDR": 0.0, "Power": 0.6, "Temporal_FDR": 0.0, "Temporal_Power": 0.6, "Average_Window_FDR": 0.0, "Average_Window_Power": 0.9137254901960784, "Window_Overlap": {"0": 0.9705882352941176, "3": 1.0, "4": 0.9}}, "40": {"FDR": 0.0, "Power": 0.8, "Temporal_FDR": 0.0, "Temporal_Power": 0.6, "Average_Window_FDR": 0.0, "Average_Window_Power": 0.9803921568627452, "Window_Overlap": {"0": 0.9705882352941176, "3": 1.0, "4": 1.0}}, "80": {"FDR": 0.0, "Power": 0.8, "Temporal_FDR": 0.0, "Temporal_Power": 0.8, "Average_Window_FDR": 0.0, "Average_Window_Power": 0.9166666666666666, "Window_Overlap": {"0": 1.0, "2": 0.8333333333333333, "3": 1.0, "4": 1.0}}, "160": {"FDR": 0.0, "Power": 0.8, "Temporal_FDR": 0.0, "Temporal_Power": 0.8, "Average_Window_FDR": 0.0, "Average_Window_Power": 1.0, "Window_Overlap": {"0": 1.0, "2": 1.0, "3": 1.0, "4": 1.0}}, "320": {"FDR": 0.0, "Power": 0.8, "Temporal_FDR": 0.0, "Temporal_Power": 0.8, "Average_Window_FDR": 0.0, "Average_Window_Power": 1.0, "Window_Overlap": {"0": 1.0, "2": 1.0, "3": 1.0, "4": 1.0}}}